example1_mxmul_pkg/__init__.py
example1_mxmul_pkg/mxmul.py
example1_mxmul_pkg-0.1.0.dist-info/LICENSE
example1_mxmul_pkg-0.1.0.dist-info/METADATA
example1_mxmul_pkg-0.1.0.dist-info/WHEEL
example1_mxmul_pkg-0.1.0.dist-info/top_level.txt
example1_mxmul_pkg-0.1.0.dist-info/RECORD
