Metadata-Version: 2.1
Name: example1-mxmul-pkg
Version: 0.1.0
Summary: An example for teaching how to publish a Python package
Home-page: https://github.com/pypa/sampleproject
Author: Feng Le
Author-email: 201130933@qq.com
License: UNKNOWN
Platform: UNKNOWN
Classifier: Programming Language :: Python :: 3
Classifier: License :: OSI Approved :: MIT License
Classifier: Operating System :: OS Independent
Requires-Python: >=3.6
License-File: LICENSE
